README.md
setup.py
src/VBW/__init__.py
src/VBW/main.py
src/VBW.egg-info/PKG-INFO
src/VBW.egg-info/SOURCES.txt
src/VBW.egg-info/dependency_links.txt
src/VBW.egg-info/top_level.txt
src/VBW/VBCore/VBError.py
src/VBW/VBCore/VBInterpreterProcess.py
src/VBW/VBCore/VBObjectWrapper.py
src/VBW/VBCore/VBWrapperBase.py
src/VBW/VBCore/__init__.py
src/VBW/VBCore/interactive_interpreter.vbs
src/VBW/VBWrappers/VBWrapperComplexExcel.py
src/VBW/VBWrappers/VBWrapperShell.py
src/VBW/VBWrappers/VBWrapperSimpleExcel.py
src/VBW/VBWrappers/__init__.py